ProcyonCLSSDK/__init__.py
ProcyonCLSSDK/ekernel.py
ProcyonCLSSDK/kernel.py
ProcyonCLS_SDK-2.1.0.dist-info/LICENSE
ProcyonCLS_SDK-2.1.0.dist-info/METADATA
ProcyonCLS_SDK-2.1.0.dist-info/WHEEL
ProcyonCLS_SDK-2.1.0.dist-info/top_level.txt
ProcyonCLS_SDK-2.1.0.dist-info/RECORD
